{
  "studios": [
    {
      "name": "Example Yoga Studio",
      "url": "https://www.exampleyoga.com/schedule",
      "color": "#c17a5c",
      "enabled": true,
      "notes": "Replace this with a real studio URL. See README for scraping setup."
    },
    {
      "name": "Sunrise Wellness Center",
      "url": "https://www.sunrisewellness.com/classes",
      "color": "#7a9e7e",
      "enabled": false,
      "notes": "Set enabled: true once you've configured the scraper for this site."
    }
  ]
}
